setup.py
multipleiterator/__init__.py
multipleiterator.egg-info/PKG-INFO
multipleiterator.egg-info/SOURCES.txt
multipleiterator.egg-info/dependency_links.txt
multipleiterator.egg-info/not-zip-safe
multipleiterator.egg-info/top_level.txt