Metadata-Version: 1.0
Name: multipleiterator
Version: 0.0.1
Summary: Iterate multiple list
Home-page: https://github.com/ipconfiger/multipleiterator
Author: Alexander.Li
Author-email: superpowerlee@gmail.com
License: MIT License
Platform: UNKNOWN
